json_converter/__init__.py
json_converter/data_node.py
json_converter/json_mapper.py
json_converter/post_process.py
json_converter-0.5.0.dist-info/METADATA
json_converter-0.5.0.dist-info/WHEEL
json_converter-0.5.0.dist-info/top_level.txt
json_converter-0.5.0.dist-info/RECORD
