Metadata-Version: 2.1
Name: json-converter
Version: 0.5.0
Summary: json-converter is a tool for translating/converting a JSON document into another JSON document with a different structure.
Home-page: https://github.com/ebi-ait/json-converter
License: UNKNOWN
Platform: UNKNOWN
Classifier: Development Status :: 3 - Alpha
Classifier: Programming Language :: Python :: 3
Classifier: License :: OSI Approved :: Apache Software License
Classifier: Operating System :: OS Independent
